setup.cfg
setup.py
json_xml_serializer.egg-info/PKG-INFO
json_xml_serializer.egg-info/SOURCES.txt
json_xml_serializer.egg-info/dependency_links.txt
json_xml_serializer.egg-info/requires.txt
json_xml_serializer.egg-info/top_level.txt
serializers/__init__.py
serializers/consts.py
serializers/factory.py
serializers/packing_tool.py
serializers/serializer.py
serializers/serializer_json.py
serializers/serializer_xml.py
test/test_value.py
test/tests.py