Metadata-Version: 2.1
Name: json-xml-serializer
Version: 0.1.1
Summary: Library for python (de)serialization in Json and Xml
Home-page: https://github.com/panton8/igi-labs/tree/lab3
Author: Anton Padvalnikau
Author-email: podvalnikov0@gmail.com
License: MIT
Classifier: Intended Audience :: Developers
Classifier: Programming Language :: Python :: 3.10
Classifier: Operating System :: OS Independent
